longeval/evaluate_linkers.py
longeval/linkage/longchecker/allennlp_feedforward.py
longeval/linkage/longchecker/allennlp_nn_util.py
longeval/linkage/longchecker/data.py
longeval/linkage/longchecker/metrics.py
longeval/linkage/longchecker/model.py
longeval/linkage/longchecker/predict.py
longeval/linkage/longchecker/train.py
longeval/linkage/longchecker/util.py
longeval/linkage/multivers_utils.py
longeval/linkage/similarity/__init__.py
longeval/linkage/similarity/sim/.gitkeep
longeval/linkage/similarity/sim_models.py
longeval/linkage/similarity/sim_utils.py
longeval/linkage/similarity/test_sim.py
longeval/linkage/summac/LICENSE
longeval/linkage/summac/README.md
longeval/linkage/summac/SummaC - Additional Experiments.ipynb
longeval/linkage/summac/SummaC - Main Results.ipynb
longeval/linkage/summac/generate_granularity_script.py
longeval/linkage/summac/model_baseline.py
longeval/linkage/summac/model_guardrails.py
longeval/linkage/summac/model_summac.py
longeval/linkage/summac/requirements.txt
longeval/linkage/summac/run_baseline.py
longeval/linkage/summac/run_kis_summac.py
longeval/linkage/summac/run_summac_precomp.py
longeval/linkage/summac/script.sh
longeval/linkage/summac/summac_conv_vitc_sent_perc_e.bin
longeval/linkage/summac/train_summac.py
longeval/linkage/summac/utils_frank_evaluation.py
longeval/linkage/summac/utils_misc.py
longeval/linkage/summac/utils_optim.py
longeval/linkage/summac/utils_scorer.py
longeval/linkage/summac/utils_scoring.py
longeval/linkage/summac/utils_summac_benchmark.py
longeval/linkage/summac_utils.py
longeval/linkage/superpal_utils.py
longeval/linkage/utils.py
longeval/metrics/bart_score.py
longeval/metrics/metric_utils.py
longeval/metrics/plot_violin_utils.py
longeval/metrics/time_utils.py
longeval/metrics_corr_confidence_pubmed.py
longeval/metrics_corr_confidence_squality.py
longeval/prepare_summaries.py
longeval/preprocessing_utils.py
longeval/results_utils.py
longeval/utils.py
longeval-0.1.3.dist-info/METADATA
longeval-0.1.3.dist-info/LICENSE
longeval-0.1.3.dist-info/WHEEL
longeval-0.1.3.dist-info/RECORD
