Metadata-Version: 2.1
Name: longeval
Version: 0.1.3
Summary: Prepare your summarization data in a format compatible with the longeval guidelines for human evaluation.
Home-page: https://github.com/martiansideofthemoon/longeval-summarization
License: Apache-2.0
Author: Kalpesh Krishna, Erin Bransom, Bailey Kuehl, Mohit Iyyer, Pradeep Dasigi, Arman Cohan, Kyle Lo
Requires-Python: >=3.7,<4.0
Classifier: License :: OSI Approved :: Apache Software License
Classifier: Programming Language :: Python :: 3
Classifier: Programming Language :: Python :: 3.7
Classifier: Programming Language :: Python :: 3.8
Classifier: Programming Language :: Python :: 3.9
Classifier: Programming Language :: Python :: 3.10
Classifier: Programming Language :: Python :: 3.11
Requires-Dist: bert-score (>=0.3.12,<0.4.0)
Requires-Dist: nltk (>=3.8.1,<4.0.0)
Requires-Dist: pandas (==1.1)
Requires-Dist: pytorch-lightning (==1.2.1)
Requires-Dist: rank-bm25 (>=0.2.2,<0.3.0)
Requires-Dist: rouge-score (>=0.1.2,<0.2.0)
Requires-Dist: sentencepiece (>=0.1.97,<0.2.0)
Requires-Dist: spacy (==3.0.0)
Requires-Dist: statsmodels (>=0.13.5,<0.14.0)
Requires-Dist: torch (>=1.13.1,<2.0.0)
Requires-Dist: tqdm (>=4.64.1,<5.0.0)
Requires-Dist: transformers (>=4.26.0,<5.0.0)
Project-URL: Repository, https://github.com/martiansideofthemoon/longeval-summarization
